setup.py
test.py
my_test_unknown.egg-info/PKG-INFO
my_test_unknown.egg-info/SOURCES.txt
my_test_unknown.egg-info/dependency_links.txt
my_test_unknown.egg-info/top_level.txt